{"caregivers": {
   "Lauryn Wairimu": {
        "id": 1,
        
        "experience": "5 years of experience in elderly care.",
        "certification": "Certified Nursing Assistant",
        "image": "images2/ass1.jpg"
    },
    "Rsper Wangui":{
        "id": 2,
        
        "experience": "3 years of experience in pediatric care.",
        "certification": "Pediatric Care Specialist",
        "image": "images2/ass2.jpg"
    },
    
    "Slyivia Wangui":{
        "id": 3,
      
        "experience": "34years of experience in orthopeditric.",
        "certification": " Orthopeditric Specialist",
        "image": "images2/ass3.jpg"
    },
    "Mareen Kamunge":{
        "id": 4,
      
        "experience": "6 years of experience in Eledery  Care.",
        "certification": "Certified Nursing Assistant",
        "image": "images2/ass4.jpg"
    },
    
    "Rsper Wambui":{
        "id": 5,
       
        "experience": "3 years of experience in Eledery  Care.",
        "certification": "Certified Nursing Assistant",
        "image": "images2/ass5.jpg"
    },
    "Irene Kiprono":{
        "id": 6,
    
        "experience": "6 years of experience in Eledery  Care.",
        "certification": "Certified Nursing Assistant",
        "image": "images2/ass6.jpg"
    },
    "Elizabeth Wairimu":{
        "id": 7,
       
        "experience": "3 years of experience in Eledery  Care.",
        "certification": "Certified Nursing Assistantt",
        "image": "images2/ass7.jpg"
    },
   
    "Consalata Waithera": {
        "id": 8,
       
        "experience": "3 years of experience in Eledery  Care.",
        "certification": "Certified Nursing Assistant",
        "image": "images2/ass8.jpg"
    }
},
"reviews":[
    {
        "id":1,
        "user": "kimani",
        "comment": "Time well utilized and I feel comfortable ."
    
    }
]


}
